mlops_project_mkamalov/__init__.py
mlops_project_mkamalov/config.py
mlops_project_mkamalov/dataset.py
mlops_project_mkamalov/features.py
mlops_project_mkamalov/plots.py
mlops_project_mkamalov/modeling/__init__.py
mlops_project_mkamalov/modeling/predict.py
mlops_project_mkamalov/modeling/train.py
mlops_project_mkamalov-0.0.1.dist-info/WHEEL
mlops_project_mkamalov-0.0.1.dist-info/METADATA
mlops_project_mkamalov-0.0.1.dist-info/RECORD
