Metadata-Version: 2.4
Name: mlops_project_mkamalov
Version: 0.0.1
Summary: A short description of the project.
Author: Marat Kamalov
Requires-Python: ~=3.10
Classifier: Programming Language :: Python :: 3
